typed_json_dataclass/__init__.py
typed_json_dataclass/typed_json_dataclass.py
typed_json_dataclass/utils.py
typed_json_dataclass-1.2.1.dist-info/LICENSE
typed_json_dataclass-1.2.1.dist-info/WHEEL
typed_json_dataclass-1.2.1.dist-info/METADATA
typed_json_dataclass-1.2.1.dist-info/RECORD
