Metadata-Version: 2.1
Name: typed-json-dataclass
Version: 1.2.1
Summary: Make your dataclasses automatically validate their types
Home-page: http://github.com/abatilo/typed_json_dataclass
License: MIT
Keywords: dataclasses,dataclass,json,mypy,pyre,marshmallow,attrs,cattrs
Author: Aaron
Author-email: AaronBatilo@gmail.com
Requires-Python: >=3.7,<4.0
Classifier: Development Status :: 5 - Production/Stable
Classifier: Environment :: Web Environment
Classifier: Intended Audience :: Developers
Classifier: License :: OSI Approved :: MIT License
Classifier: Programming Language :: Python :: 3
Classifier: Programming Language :: Python :: 3.7
Classifier: Topic :: Software Development :: Libraries :: Python Modules
Requires-Dist: flake8-tuple (>=0.4.0,<0.5.0)
Project-URL: Repository, http://github.com/abatilo/typed_json_dataclass
